gamebook/__init__.py
gamebook/constants.py
gamebook/creature.py
gamebook/exceptions.py
gamebook/fight_scene.py
gamebook/game_input.py
gamebook/game_manager.py
gamebook/helpers.py
gamebook/hero.py
gamebook/input_interface.py
gamebook/monster.py
gamebook/nextscene.py
gamebook/option.py
gamebook/output.py
gamebook/output_interface.py
gamebook/scene.py
gamebook/terminal_input.py
gamebook/terminal_output.py
gamebook/trait.py
gamebook_maker-0.2.0.dist-info/METADATA
gamebook_maker-0.2.0.dist-info/WHEEL
gamebook_maker-0.2.0.dist-info/top_level.txt
gamebook_maker-0.2.0.dist-info/RECORD
